MANIFEST.in
README.rst
setup.py
dropboxwsgi/__init__.py
dropboxwsgi/_version.py
dropboxwsgi/caching.py
dropboxwsgi/dropboxwsgi.py
dropboxwsgi/main.py
dropboxwsgi/six.py
dropboxwsgi.egg-info/PKG-INFO
dropboxwsgi.egg-info/SOURCES.txt
dropboxwsgi.egg-info/dependency_links.txt
dropboxwsgi.egg-info/entry_points.txt
dropboxwsgi.egg-info/requires.txt
dropboxwsgi.egg-info/top_level.txt