Metadata-Version: 1.1
Name: dropboxwsgi
Version: 1.0.1
Summary: WSGI-compatible HTTP interface to Dropbox
Home-page: https://github.com/rianhunter/dropboxwsgi
Author: Rian Hunter
Author-email: rian@alum.mit.edu
License: MIT License
Keywords: networking
Platform: UNKNOWN
Classifier: Development Status :: 5 - Production/Stable
Classifier: Environment :: No Input/Output (Daemon)
Classifier: Intended Audience :: Developers
Classifier: Intended Audience :: System Administrators
Classifier: License :: OSI Approved :: MIT License
Classifier: Operating System :: OS Independent
Classifier: Programming Language :: Python
Classifier: Programming Language :: Python :: 2
Classifier: Programming Language :: Python :: 3
Classifier: Topic :: Internet :: WWW/HTTP
Classifier: Topic :: System :: Networking
Classifier: Topic :: Software Development :: Libraries :: Python Modules
